README.md
setup.py
razrda_binomial_options_pricing.egg-info/PKG-INFO
razrda_binomial_options_pricing.egg-info/SOURCES.txt
razrda_binomial_options_pricing.egg-info/dependency_links.txt
razrda_binomial_options_pricing.egg-info/requires.txt
razrda_binomial_options_pricing.egg-info/top_level.txt
razrda_binomialoptionspricing/BinomialOptionsPricing.py
razrda_binomialoptionspricing/__init__.py
razrda_binomialoptionspricing/example.py