Metadata-Version: 1.0
Name: razrda-binomial-options-pricing
Version: 1.0.2
Summary: Binomial Options Pricing for European and Amrerican. Suitable for Visualizations.
Home-page: UNKNOWN
Author: Muhammad Raza
Author-email: UNKNOWN
License: UNKNOWN
Platform: UNKNOWN
